<phase-doc>
  <metadata>
    <phase id="02" />
    <doc-type>RESEARCH</doc-type>
    <source>.planning/phases/02-planning-docs-cleanup-and-narrative-state-space-simulations/02-RESEARCH.xml</source>
    <generated-at>2026-03-03</generated-at>
  </metadata>
  <legacy>
    <content><![CDATA[
# Phase 02: Planning docs cleanup and narrative state-space simulations - Research

**Researched:** 2026-02-24T03:45:05.160Z

## Summary

Research stub generated by Forge Loop. Fill with concrete stack/pattern findings before deep implementation when needed.

## User Constraints

- Preserve phase scope from roadmap and context docs.

## Recommended Stack

- Reuse existing forge-agent conventions from AGENTS.md and current package architecture.

## Pitfalls

- Avoid introducing parallel source-of-truth artifacts outside .planning.

]]></content>
  </legacy>
</phase-doc>



